geoassistant/__init__.py
geoassistant/blasting/BlastingCatalog.py
geoassistant/blasting/BlastingEvent.py
geoassistant/blasting/BlastingEventsCollection.py
geoassistant/blasting/__init__.py
geoassistant/block_model/BlockModel.py
geoassistant/block_model/BlockModelField.py
geoassistant/block_model/__init__.py
geoassistant/block_model/components/BlockModelPositions.py
geoassistant/block_model/components/BlockModelProperties.py
geoassistant/block_model/components/BlockModelReader.py
geoassistant/block_model/components/BlockModelReporter.py
geoassistant/block_model/components/BlockModelSubsetter.py
geoassistant/block_model/components/BlockModelWriter.py
geoassistant/block_model/components/__init__.py
geoassistant/block_model/field_components/BlockModelFieldAnalyzer.py
geoassistant/block_model/field_components/__init__.py
geoassistant/ground_support/__init__.py
geoassistant/ground_support/displacement_based/__init__.py
geoassistant/ground_support/displacement_based/catalogs/__init__.py
geoassistant/ground_support/displacement_based/demand_elements/BulkingFactors.py
geoassistant/ground_support/displacement_based/demand_elements/DemandSystem.py
geoassistant/ground_support/displacement_based/demand_elements/DisplacementDemand.py
geoassistant/ground_support/displacement_based/demand_elements/EnergyDemand.py
geoassistant/ground_support/displacement_based/demand_elements/PreviousDisplacement.py
geoassistant/ground_support/displacement_based/demand_elements/SeismicResponse.py
geoassistant/ground_support/displacement_based/demand_elements/ShakedownDemand.py
geoassistant/ground_support/displacement_based/demand_elements/StaticDemand.py
geoassistant/ground_support/displacement_based/demand_elements/Strainburst.py
geoassistant/ground_support/displacement_based/demand_elements/UnstableMass.py
geoassistant/ground_support/displacement_based/demand_elements/__init__.py
geoassistant/ground_support/displacement_based/demand_elements/bulkingfactors_components/BulkingFactorsProperties.py
geoassistant-0.0.2.dist-info/METADATA
geoassistant-0.0.2.dist-info/WHEEL
geoassistant-0.0.2.dist-info/top_level.txt
geoassistant-0.0.2.dist-info/RECORD
